setup.py
pydinogame/Builder.py
pydinogame/__init__.py
pydinogame.egg-info/PKG-INFO
pydinogame.egg-info/SOURCES.txt
pydinogame.egg-info/dependency_links.txt
pydinogame.egg-info/requires.txt
pydinogame.egg-info/top_level.txt
pydinogame/sprites/cacti-big.png
pydinogame/sprites/cacti-small.png
pydinogame/sprites/checkPoint.wav
pydinogame/sprites/cloud.png
pydinogame/sprites/die.wav
pydinogame/sprites/dino.png
pydinogame/sprites/dino_ducking.png
pydinogame/sprites/game_over.png
pydinogame/sprites/ground.png
pydinogame/sprites/jump.wav
pydinogame/sprites/logo.png
pydinogame/sprites/numbers.png
pydinogame/sprites/offline-sprite-2x-black.png
pydinogame/sprites/ptera.png
pydinogame/sprites/replay_button.png