Metadata-Version: 2.1
Name: pydinogame
Version: 0.1.3
Summary: Dino game builder
Author: Ho Anh Tuan
Author-email: author@example.com
Classifier: Programming Language :: Python :: 2
Classifier: License :: OSI Approved :: MIT License
Classifier: Operating System :: OS Independent
